.dockerignore
.env.run-docker
.env.run-local
.env.test-docker
.env.test-local
.gitattributes
.gitignore
CONTRIBUTING.md
Dockerfile
LICENSE
Makefile
README.md
docker-cmd.sh
docker-compose.run.yml
docker-compose.test.yml
docker-compose.yml
mkdocs.yml
pyproject.toml
uv.lock
.github/ISSUE_TEMPLATE/bug.md
.github/ISSUE_TEMPLATE/feature_request.md
.github/ISSUE_TEMPLATE/general.md
.github/workflows/check-docs.yml
.github/workflows/publish-pypi.yml
.github/workflows/publish.yml
.github/workflows/run-tests.yml
app/__init__.py
app/__main__.py
app/application.py
app/config.py
app/errors.py
app/logger.py
app/dependencies/__init__.py
app/dependencies/accounting.py
app/dependencies/auth.py
app/dependencies/entitysdk.py
app/dependencies/launchsystem.py
app/endpoints/__init__.py
app/endpoints/circuit_connectivity.py
app/endpoints/circuit_properties.py
app/endpoints/count_scan_coordinates.py
app/endpoints/ephys_metrics.py
app/endpoints/mesh_validation.py
app/endpoints/morphology_metrics.py
app/endpoints/morphology_metrics_calculation.py
app/endpoints/morphology_template.json
app/endpoints/morphology_validation.py
app/endpoints/multi_values.py
app/endpoints/scan_config.py
app/endpoints/task_launch.py
app/endpoints/validate_electrophysiology_protocol_nwb.py
app/endpoints/useful_functions/__init__.py
app/endpoints/useful_functions/useful_functions.py
app/schemas/__init__.py
app/schemas/auth.py
app/schemas/base.py
app/utils/__init__.py
app/utils/common.py
app/utils/http.py
docs/index.md
docs/scircuit.md
docs/scs.md
docs/gui-definition-spec/gui-definition.md
docs/gui-definition-spec/components/block_dictionary/block_dictionary.md
docs/gui-definition-spec/components/block_dictionary/designs/block_dictionary.png
docs/gui-definition-spec/components/block_dictionary/reference_schemas/block_dictionary.jsonc
docs/gui-definition-spec/components/block_single/block_single.md
docs/gui-definition-spec/components/block_single/reference_schemas/block_single.jsonc
obi_one.egg-info/PKG-INFO
obi_one.egg-info/SOURCES.txt
obi_one.egg-info/dependency_links.txt
obi_one.egg-info/requires.txt
obi_one.egg-info/top_level.txt
