Metadata-Version: 2.4
Name: obi-one
Version: 2026.1.7
Summary: Standardized library of functions and workflows for biophysically-detailed brain modeling
Author-email: James Isbister <james.isbister@openbraininstitute.org>, Christoph Pokorny <christoph.pokorny@openbraininstitute.org>, Daniela Egas Santander <daniela.egassantander@openbraininstitute.org>, Gianluca Ficarelli <gianluca.ficarelli@openbraininstitute.org>, Michael Reimann <michael.reimann@openbraininstitute.org>, Darshan Mandge <darshan.mandge@openbraininstitute.org>, Ilkan Kilic <ilkan.kilic@openbraininstitute.org>, Aurélien Jaquier <aurelien.jaquier@openbraininstitute.org>, Dries Ver
License-Expression: Apache-2.0
Project-URL: Homepage, https://github.com/openbraininstitute/obi-one
Project-URL: Issues, https://github.com/openbraininstitute/obi-one/issues
Classifier: Programming Language :: Python :: 3
Classifier: Operating System :: OS Independent
Requires-Python: <3.13,>=3.12.2
License-File: LICENSE
Requires-Dist: pydantic>=2.10.6
Requires-Dist: pydantic-settings>=2.8.1
Requires-Dist: pydantic-core
Requires-Dist: brainbuilder>=0.20.2
Requires-Dist: bluepysnap>=3.0.2
Requires-Dist: fastapi
Requires-Dist: uvicorn
Requires-Dist: starlette
Requires-Dist: python-multipart
Requires-Dist: jupyter
Requires-Dist: notebook
Requires-Dist: jupyterlab>=4.4.8
Requires-Dist: ipykernel
Requires-Dist: sqlalchemy
Requires-Dist: blueetl
Requires-Dist: aiofiles
Requires-Dist: neurom
Requires-Dist: morph-tool
Requires-Dist: pyvista
Requires-Dist: entitysdk
Requires-Dist: obi-auth>=1.0.0
Requires-Dist: networkx>=3.4.2
Requires-Dist: pyjwt>=2.10.1
Requires-Dist: cachetools>=5.5.2
Requires-Dist: httpx>=0.28.1
Requires-Dist: bluepyefe>=2.3.51
Requires-Dist: connectome-utilities>=0.4.11
Requires-Dist: connectome-manipulator>=1.0.4
Requires-Dist: bluecellulab>=2.6.71
Requires-Dist: obi_notebook
Requires-Dist: morph_spines
Requires-Dist: caveclient>=7.11.0
Requires-Dist: obp-accounting-sdk>=0.4.2
Provides-Extra: connectivity
Requires-Dist: connectome-analysis>=1.0.1; extra == "connectivity"
Dynamic: license-file
